google_structlog/__init__.py
google_structlog/setup.py
google_structlog/setup_google.py
google_structlog/setup_stdout.py
google_structlog-43.12.0.dist-info/LICENSE
google_structlog-43.12.0.dist-info/METADATA
google_structlog-43.12.0.dist-info/WHEEL
google_structlog-43.12.0.dist-info/top_level.txt
google_structlog-43.12.0.dist-info/RECORD
