Metadata-Version: 2.1
Name: google-structlog
Version: 43.12.0
Summary: Send queryable JSON structured logs to Google Cloud (GCP) stackdriver from python apps
Home-page: UNKNOWN
Author: Seth Nickell
Author-email: snickell@gmail.com
License: UNKNOWN
Platform: UNKNOWN
Classifier: Programming Language :: Python :: 3
Classifier: Operating System :: OS Independent
Requires-Python: >=3.7
Requires-Dist: google-cloud-logging (==1.15.1)
Requires-Dist: python-json-logger
Requires-Dist: structlog
